blockchain_certificates/__init__.py
blockchain_certificates/chainpoint.py
blockchain_certificates/create_certificates.py
blockchain_certificates/cred_protocol.py
blockchain_certificates/issue_certificates.py
blockchain_certificates/network_utils.py
blockchain_certificates/pdf_utils.py
blockchain_certificates/publish_hash.py
blockchain_certificates/revoke_certificates.py
blockchain_certificates/utils.py
blockchain_certificates/validate_certificates.py
blockchain_certificates/java/FillPdf.class
blockchain_certificates/java/FillPdf.java
blockchain_certificates-2.1.9.dist-info/LICENSE.txt
blockchain_certificates-2.1.9.dist-info/METADATA
blockchain_certificates-2.1.9.dist-info/WHEEL
blockchain_certificates-2.1.9.dist-info/entry_points.txt
blockchain_certificates-2.1.9.dist-info/top_level.txt
blockchain_certificates-2.1.9.dist-info/RECORD
