Metadata-Version: 2.1
Name: blockchain-certificates
Version: 2.1.9
Summary: Create pdf certificate files and issue on the blockchain!
Home-page: https://github.com/verifiable-pdfs/blockchain-certificates
Author: Konstantinos Karasavvas
Author-email: kkarasavvas@gmail.com
License: AGPLv3
Keywords: blockchain academic certificates
Platform: UNKNOWN
Requires-Dist: pdfrw (==0.3)
Requires-Dist: fpdf (==1.7.2)
Requires-Dist: configargparse (==0.11.0)
Requires-Dist: merkletools (==1.0.3)
Requires-Dist: bitcoin-utils (>=0.5.4)
Requires-Dist: litecoin-utils (>=0.5.4)
